jupyter_book/__init__.py
jupyter_book/__main__.py
jupyter_book/nodeenv.py
jupyter_book/dist/jupyter-book.cjs
jupyter_book-2.1.0.dist-info/METADATA
jupyter_book-2.1.0.dist-info/WHEEL
jupyter_book-2.1.0.dist-info/entry_points.txt
jupyter_book-2.1.0.dist-info/licenses/LICENSE
jupyter_book-2.1.0.dist-info/RECORD
