Metadata-Version: 2.4
Name: jupyter-book
Version: 2.1.0
Dynamic: Author
Dynamic: Author-email
Dynamic: Summary
Dynamic: Keywords
Dynamic: License
Dynamic: License-Expression
Dynamic: Project-URL
License-File: LICENSE
Classifier: Development Status :: 3 - Alpha
Classifier: License :: OSI Approved :: BSD License
Classifier: Programming Language :: Python :: 3
Classifier: Programming Language :: Python :: 3 :: Only
Classifier: Programming Language :: Python :: 3.9
Classifier: Programming Language :: Python :: 3.10
Classifier: Programming Language :: Python :: 3.11
Classifier: Programming Language :: Python :: 3.12
Classifier: Programming Language :: Python :: Implementation :: CPython
Classifier: Topic :: Software Development :: Libraries :: Python Modules
Classifier: Topic :: Text Processing :: Markup
Requires-Python: >=3.9
Requires-Dist: ipykernel
Requires-Dist: jupyter-core
Requires-Dist: jupyter-server
Requires-Dist: platformdirs>=4.2.2
Requires-Dist: nodeenv>=1.9.1
Provides-Extra: docs
Requires-Dist: markdown; extra == 'docs'
Requires-Dist: pandas; extra == 'docs'
